portforward/__init__.py
portforward/_portforward.cpython-311-s390x-linux-gnu.so
portforward/_portforward.pyi
portforward/py.typed
portforward-0.7.6.dist-info/METADATA
portforward-0.7.6.dist-info/WHEEL
portforward-0.7.6.dist-info/licenses/AUTHORS.rst
portforward-0.7.6.dist-info/licenses/LICENSE
portforward-0.7.6.dist-info/RECORD
