Metadata-Version: 2.4
Name: portforward
Version: 0.7.6
Classifier: Programming Language :: Rust
Classifier: Programming Language :: Python :: Implementation :: CPython
Classifier: Programming Language :: Python :: Implementation :: PyPy
Classifier: Programming Language :: Python :: 3
Classifier: Programming Language :: Python :: 3.7
Classifier: Programming Language :: Python :: 3.8
Classifier: Programming Language :: Python :: 3.9
Classifier: Programming Language :: Python :: 3.10
Classifier: Programming Language :: Python :: 3.11
Classifier: Programming Language :: Python :: 3.12
Classifier: Programming Language :: Python :: 3.13
Classifier: Programming Language :: Python :: 3.14
License-File: LICENSE
License-File: AUTHORS.rst
Summary: Easy Kubernetes Port-Forward For Python
Keywords: portforward,kubernetes,k8s
Author-email: Sebastian Ziemann <corka149@mailbox.org>
License: MIT License
Requires-Python: >=3.7
Project-URL: Changelog, https://github.com/pytogo/portforward/blob/main/HISTORY.rst
Project-URL: Documentation, https://portforward.readthedocs.io
Project-URL: Repository, https://github.com/pytogo/portforward.git
